dcc_rpi_encoder_c
dccpi
