Metadata-Version: 1.1
Name: dccpi
Version: 1.3.1
Summary: A Python NMRA DCC protocol implementation for RaspberryPi
Home-page: https://github.com/hsanjuan/dccpi
Author: Hector Sanjuan
Author-email: code@hector.link
License: GNU General Public License v3 (GPLv3)
Keywords: dcc,nrma,pi,raspberry,modelling,train,decoder,command,station,loco,locomotive
Platform: UNKNOWN
Classifier: Programming Language :: Python :: 2.7
Classifier: Programming Language :: Python :: 3
Classifier: License :: OSI Approved :: GNU General Public License v3 (GPLv3)
Classifier: Development Status :: 4 - Beta
Classifier: Environment :: Plugins
Classifier: Intended Audience :: Developers
Classifier: Natural Language :: English
Classifier: Operating System :: POSIX :: Linux
Classifier: Topic :: System :: Networking
Classifier: Topic :: Software Development :: Libraries :: Python Modules
